langchain_unstructured/__init__.py
langchain_unstructured/document_loaders.py
langchain_unstructured/py.typed
langchain_unstructured-1.0.0.dist-info/LICENSE
langchain_unstructured-1.0.0.dist-info/METADATA
langchain_unstructured-1.0.0.dist-info/WHEEL
langchain_unstructured-1.0.0.dist-info/RECORD
